mrsimulator/base_model.cp311-win_amd64.pyd
mrsimulator/benchmark.py
mrsimulator/clib.cp311-win_amd64.pyd
mrsimulator/methods.py
mrsimulator/__init__.py
mrsimulator/__main__.py
mrsimulator/method/event.py
mrsimulator/method/frequency_contrib.py
mrsimulator/method/plot.py
mrsimulator/method/query.py
mrsimulator/method/spectral_dimension.py
mrsimulator/method/utils.py
mrsimulator/method/__init__.py
mrsimulator/method/lib/base.py
mrsimulator/method/lib/correlation.py
mrsimulator/method/lib/mqvas.py
mrsimulator/method/lib/ssb2d.py
mrsimulator/method/lib/stvas.py
mrsimulator/method/lib/test_affine_matrix.py
mrsimulator/method/lib/__init__.py
mrsimulator/method/tests/lib_tests/test_data.json
mrsimulator/models/analytical_distributions.py
mrsimulator/models/czjzek.py
mrsimulator/models/utils.py
mrsimulator/models/__init__.py
mrsimulator/signal_processor/affine.py
mrsimulator/signal_processor/apodization.py
mrsimulator/signal_processor/baseline.py
mrsimulator/signal_processor/utils.py
mrsimulator/signal_processor/_base.py
mrsimulator/signal_processor/__init__.py
mrsimulator/signal_processor/tests/test_affine.py
mrsimulator/signal_processor/tests/test_apodization.py
mrsimulator/signal_processor/tests/test_baseline.py
mrsimulator/signal_processor/tests/test_signal_processor.py
mrsimulator/signal_processor/tests/__init__.py
mrsimulator/simulator/config.py
mrsimulator/simulator/sampling_scheme.py
mrsimulator/simulator/__init__.py
mrsimulator/spin_system/coupling.py
mrsimulator/spin_system/isotope.py
mrsimulator/spin_system/isotope_data.json
mrsimulator/spin_system/references.json
mrsimulator/spin_system/site.py
mrsimulator/spin_system/split_spinsystems.py
mrsimulator/spin_system/tensors.py
mrsimulator/spin_system/zeemanstate.py
mrsimulator/spin_system/__init__.py
mrsimulator/tests/tests.cp311-win_amd64.pyd
mrsimulator/tests/test_mrsimulator_class.py
mrsimulator/tests/test_root_level_funcs.py
mrsimulator/tests/__init__.py
mrsimulator/transition/base.py
mrsimulator-1.0.0.dist-info/DELVEWHEEL
mrsimulator-1.0.0.dist-info/entry_points.txt
mrsimulator-1.0.0.dist-info/LICENSE
mrsimulator-1.0.0.dist-info/METADATA
mrsimulator-1.0.0.dist-info/RECORD
mrsimulator-1.0.0.dist-info/top_level.txt
mrsimulator-1.0.0.dist-info/WHEEL
