Metadata-Version: 2.1
Name: mrsimulator
Version: 1.0.0
Summary: A python toolbox for simulating fast real-time solid-state NMR spectra.
Home-page: https://github.com/deepanshs/mrsimulator/
Author: Deepansh J. Srivastava
Author-email: srivastava.89@osu.edu
License: BSD-3-Clause
Classifier: Intended Audience :: Science/Research
Classifier: Intended Audience :: Education
Classifier: Intended Audience :: Developers
Classifier: Operating System :: OS Independent
Classifier: Development Status :: 4 - Beta
Classifier: License :: OSI Approved :: BSD License
Classifier: Programming Language :: C
Classifier: Programming Language :: Python :: 3
Classifier: Programming Language :: Python :: 3.10
Classifier: Programming Language :: Python :: 3.11
Classifier: Programming Language :: Python :: 3.12
Classifier: Programming Language :: Python :: 3.13
Classifier: Topic :: Education
Classifier: Topic :: Scientific/Engineering :: Chemistry
Classifier: Topic :: Scientific/Engineering :: Physics
Requires-Python: >=3.10
License-File: LICENSE
Requires-Dist: numpy>=1.20
Requires-Dist: csdmpy>=0.7
Requires-Dist: pydantic>=2.8
Requires-Dist: typing-extensions>=3.7
Requires-Dist: psutil>=5.4.8
Requires-Dist: joblib>=1.0.0
Requires-Dist: pandas>=1.1.3
Requires-Dist: lmfit>=1.0.2
Requires-Dist: matplotlib>=3.3.4
Requires-Dist: astropy>=6
